<?xml version="1.0" encoding="UTF-8"?>
<object-persistence xmlns="http://www.eclipse.org/eclipselink/xsds/persistence" xmlns:xsd="http://www.w3.org/2001/XMLSchema" xmlns:eclipselink="http://www.eclipse.org/eclipselink/xsds/persistence" xmlns:xsi="http://www.w3.org/2001/XMLSchema-instance" version="Eclipse Persistence Services - 2.3.1.v20111018-r10243">
   <name>SelectJDEE1DBAdaptorV1-OR</name>
   <class-mapping-descriptors>
      <class-mapping-descriptor xsi:type="object-relational-class-mapping-descriptor">
         <class>SelectJDEE1DBAdaptorV1.F5542112</class>
         <alias>F5542112</alias>
         <primary-key>
            <field table="F5542112" name="TLDCTO" xsi:type="column"/>
            <field table="F5542112" name="TLDOCO" xsi:type="column"/>
            <field table="F5542112" name="TLKCOO" xsi:type="column"/>
            <field table="F5542112" name="TLLNID" xsi:type="column"/>
         </primary-key>
         <events/>
         <querying>
            <queries>
               <query name="SelectJDEE1DBAdaptorV1Select" xsi:type="read-all-query">
                  <reference-class>SelectJDEE1DBAdaptorV1.F5542112</reference-class>
                  <container xsi:type="list-container-policy">
                     <collection-type>java.util.Vector</collection-type>
                  </container>
               </query>
            </queries>
         </querying>
         <attribute-mappings>
            <attribute-mapping xsi:type="direct-mapping">
               <attribute-name>tlkcoo</attribute-name>
               <field table="F5542112" name="TLKCOO" xsi:type="column"/>
               <attribute-classification>java.lang.String</attribute-classification>
            </attribute-mapping>
            <attribute-mapping xsi:type="direct-mapping">
               <attribute-name>tldoco</attribute-name>
               <field table="F5542112" name="TLDOCO" xsi:type="column"/>
               <attribute-classification>java.math.BigDecimal</attribute-classification>
            </attribute-mapping>
            <attribute-mapping xsi:type="direct-mapping">
               <attribute-name>tldcto</attribute-name>
               <field table="F5542112" name="TLDCTO" xsi:type="column"/>
               <attribute-classification>java.lang.String</attribute-classification>
            </attribute-mapping>
            <attribute-mapping xsi:type="direct-mapping">
               <attribute-name>tllnid</attribute-name>
               <field table="F5542112" name="TLLNID" xsi:type="column"/>
               <attribute-classification>java.math.BigDecimal</attribute-classification>
            </attribute-mapping>
            <attribute-mapping xsi:type="direct-mapping">
               <attribute-name>tlmcu</attribute-name>
               <properties>
                  <property name="enabled">
                     <value>false</value>
                  </property>
               </properties>
               <field table="F5542112" name="TLMCU" xsi:type="column"/>
               <attribute-classification>java.lang.String</attribute-classification>
            </attribute-mapping>
            <attribute-mapping xsi:type="direct-mapping">
               <attribute-name>tlan8</attribute-name>
               <properties>
                  <property name="enabled">
                     <value>false</value>
                  </property>
               </properties>
               <field table="F5542112" name="TLAN8" xsi:type="column"/>
               <attribute-classification>java.math.BigDecimal</attribute-classification>
            </attribute-mapping>
            <attribute-mapping xsi:type="direct-mapping">
               <attribute-name>tlshan</attribute-name>
               <properties>
                  <property name="enabled">
                     <value>false</value>
                  </property>
               </properties>
               <field table="F5542112" name="TLSHAN" xsi:type="column"/>
               <attribute-classification>java.math.BigDecimal</attribute-classification>
            </attribute-mapping>
            <attribute-mapping xsi:type="direct-mapping">
               <attribute-name>tlpa8</attribute-name>
               <properties>
                  <property name="enabled">
                     <value>false</value>
                  </property>
               </properties>
               <field table="F5542112" name="TLPA8" xsi:type="column"/>
               <attribute-classification>java.math.BigDecimal</attribute-classification>
            </attribute-mapping>
            <attribute-mapping xsi:type="direct-mapping">
               <attribute-name>tldrqj</attribute-name>
               <properties>
                  <property name="enabled">
                     <value>false</value>
                  </property>
               </properties>
               <field table="F5542112" name="TLDRQJ" xsi:type="column"/>
               <attribute-classification>java.lang.Integer</attribute-classification>
            </attribute-mapping>
            <attribute-mapping xsi:type="direct-mapping">
               <attribute-name>tltrdj</attribute-name>
               <properties>
                  <property name="enabled">
                     <value>false</value>
                  </property>
               </properties>
               <field table="F5542112" name="TLTRDJ" xsi:type="column"/>
               <attribute-classification>java.lang.Integer</attribute-classification>
            </attribute-mapping>
            <attribute-mapping xsi:type="direct-mapping">
               <attribute-name>tlcndj</attribute-name>
               <properties>
                  <property name="enabled">
                     <value>false</value>
                  </property>
               </properties>
               <field table="F5542112" name="TLCNDJ" xsi:type="column"/>
               <attribute-classification>java.lang.Integer</attribute-classification>
            </attribute-mapping>
            <attribute-mapping xsi:type="direct-mapping">
               <attribute-name>tlpefj</attribute-name>
               <field table="F5542112" name="TLPEFJ" xsi:type="column"/>
               <attribute-classification>java.lang.Integer</attribute-classification>
            </attribute-mapping>
            <attribute-mapping xsi:type="direct-mapping">
               <attribute-name>tlvr01</attribute-name>
               <properties>
                  <property name="enabled">
                     <value>false</value>
                  </property>
               </properties>
               <field table="F5542112" name="TLVR01" xsi:type="column"/>
               <attribute-classification>java.lang.String</attribute-classification>
            </attribute-mapping>
            <attribute-mapping xsi:type="direct-mapping">
               <attribute-name>tlvr02</attribute-name>
               <properties>
                  <property name="enabled">
                     <value>false</value>
                  </property>
               </properties>
               <field table="F5542112" name="TLVR02" xsi:type="column"/>
               <attribute-classification>java.lang.String</attribute-classification>
            </attribute-mapping>
            <attribute-mapping xsi:type="direct-mapping">
               <attribute-name>tlitm</attribute-name>
               <properties>
                  <property name="enabled">
                     <value>false</value>
                  </property>
               </properties>
               <field table="F5542112" name="TLITM" xsi:type="column"/>
               <attribute-classification>java.math.BigDecimal</attribute-classification>
            </attribute-mapping>
            <attribute-mapping xsi:type="direct-mapping">
               <attribute-name>tllitm</attribute-name>
               <field table="F5542112" name="TLLITM" xsi:type="column"/>
               <attribute-classification>java.lang.String</attribute-classification>
            </attribute-mapping>
            <attribute-mapping xsi:type="direct-mapping">
               <attribute-name>tlaitm</attribute-name>
               <properties>
                  <property name="enabled">
                     <value>false</value>
                  </property>
               </properties>
               <field table="F5542112" name="TLAITM" xsi:type="column"/>
               <attribute-classification>java.lang.String</attribute-classification>
            </attribute-mapping>
            <attribute-mapping xsi:type="direct-mapping">
               <attribute-name>tldsc1</attribute-name>
               <field table="F5542112" name="TLDSC1" xsi:type="column"/>
               <attribute-classification>java.lang.String</attribute-classification>
            </attribute-mapping>
            <attribute-mapping xsi:type="direct-mapping">
               <attribute-name>tldsc2</attribute-name>
               <properties>
                  <property name="enabled">
                     <value>false</value>
                  </property>
               </properties>
               <field table="F5542112" name="TLDSC2" xsi:type="column"/>
               <attribute-classification>java.lang.String</attribute-classification>
            </attribute-mapping>
            <attribute-mapping xsi:type="direct-mapping">
               <attribute-name>tllnty</attribute-name>
               <properties>
                  <property name="enabled">
                     <value>false</value>
                  </property>
               </properties>
               <field table="F5542112" name="TLLNTY" xsi:type="column"/>
               <attribute-classification>java.lang.String</attribute-classification>
            </attribute-mapping>
            <attribute-mapping xsi:type="direct-mapping">
               <attribute-name>tlnxtr</attribute-name>
               <properties>
                  <property name="enabled">
                     <value>false</value>
                  </property>
               </properties>
               <field table="F5542112" name="TLNXTR" xsi:type="column"/>
               <attribute-classification>java.lang.String</attribute-classification>
            </attribute-mapping>
            <attribute-mapping xsi:type="direct-mapping">
               <attribute-name>tllttr</attribute-name>
               <properties>
                  <property name="enabled">
                     <value>false</value>
                  </property>
               </properties>
               <field table="F5542112" name="TLLTTR" xsi:type="column"/>
               <attribute-classification>java.lang.String</attribute-classification>
            </attribute-mapping>
            <attribute-mapping xsi:type="direct-mapping">
               <attribute-name>tlemcu</attribute-name>
               <properties>
                  <property name="enabled">
                     <value>false</value>
                  </property>
               </properties>
               <field table="F5542112" name="TLEMCU" xsi:type="column"/>
               <attribute-classification>java.lang.String</attribute-classification>
            </attribute-mapping>
            <attribute-mapping xsi:type="direct-mapping">
               <attribute-name>tluom</attribute-name>
               <properties>
                  <property name="enabled">
                     <value>false</value>
                  </property>
               </properties>
               <field table="F5542112" name="TLUOM" xsi:type="column"/>
               <attribute-classification>java.lang.String</attribute-classification>
            </attribute-mapping>
            <attribute-mapping xsi:type="direct-mapping">
               <attribute-name>tluorg</attribute-name>
               <field table="F5542112" name="TLUORG" xsi:type="column"/>
               <attribute-classification>java.math.BigDecimal</attribute-classification>
            </attribute-mapping>
            <attribute-mapping xsi:type="direct-mapping">
               <attribute-name>tlsocn</attribute-name>
               <properties>
                  <property name="enabled">
                     <value>false</value>
                  </property>
               </properties>
               <field table="F5542112" name="TLSOCN" xsi:type="column"/>
               <attribute-classification>java.math.BigDecimal</attribute-classification>
            </attribute-mapping>
            <attribute-mapping xsi:type="direct-mapping">
               <attribute-name>tluprc</attribute-name>
               <field table="F5542112" name="TLUPRC" xsi:type="column"/>
               <attribute-classification>java.math.BigDecimal</attribute-classification>
            </attribute-mapping>
            <attribute-mapping xsi:type="direct-mapping">
               <attribute-name>tlaexp</attribute-name>
               <properties>
                  <property name="enabled">
                     <value>false</value>
                  </property>
               </properties>
               <field table="F5542112" name="TLAEXP" xsi:type="column"/>
               <attribute-classification>java.math.BigDecimal</attribute-classification>
            </attribute-mapping>
            <attribute-mapping xsi:type="direct-mapping">
               <attribute-name>tlprov</attribute-name>
               <properties>
                  <property name="enabled">
                     <value>false</value>
                  </property>
               </properties>
               <field table="F5542112" name="TLPROV" xsi:type="column"/>
               <attribute-classification>java.lang.String</attribute-classification>
            </attribute-mapping>
            <attribute-mapping xsi:type="direct-mapping">
               <attribute-name>tllprc</attribute-name>
               <properties>
                  <property name="enabled">
                     <value>false</value>
                  </property>
               </properties>
               <field table="F5542112" name="TLLPRC" xsi:type="column"/>
               <attribute-classification>java.math.BigDecimal</attribute-classification>
            </attribute-mapping>
            <attribute-mapping xsi:type="direct-mapping">
               <attribute-name>tluncs</attribute-name>
               <properties>
                  <property name="enabled">
                     <value>false</value>
                  </property>
               </properties>
               <field table="F5542112" name="TLUNCS" xsi:type="column"/>
               <attribute-classification>java.math.BigDecimal</attribute-classification>
            </attribute-mapping>
            <attribute-mapping xsi:type="direct-mapping">
               <attribute-name>tlecst</attribute-name>
               <properties>
                  <property name="enabled">
                     <value>false</value>
                  </property>
               </properties>
               <field table="F5542112" name="TLECST" xsi:type="column"/>
               <attribute-classification>java.math.BigDecimal</attribute-classification>
            </attribute-mapping>
            <attribute-mapping xsi:type="direct-mapping">
               <attribute-name>tlasn</attribute-name>
               <properties>
                  <property name="enabled">
                     <value>false</value>
                  </property>
               </properties>
               <field table="F5542112" name="TLASN" xsi:type="column"/>
               <attribute-classification>java.lang.String</attribute-classification>
            </attribute-mapping>
            <attribute-mapping xsi:type="direct-mapping">
               <attribute-name>tltax1</attribute-name>
               <properties>
                  <property name="enabled">
                     <value>false</value>
                  </property>
               </properties>
               <field table="F5542112" name="TLTAX1" xsi:type="column"/>
               <attribute-classification>java.lang.String</attribute-classification>
            </attribute-mapping>
            <attribute-mapping xsi:type="direct-mapping">
               <attribute-name>tltxa1</attribute-name>
               <properties>
                  <property name="enabled">
                     <value>false</value>
                  </property>
               </properties>
               <field table="F5542112" name="TLTXA1" xsi:type="column"/>
               <attribute-classification>java.lang.String</attribute-classification>
            </attribute-mapping>
            <attribute-mapping xsi:type="direct-mapping">
               <attribute-name>tlexr1</attribute-name>
               <properties>
                  <property name="enabled">
                     <value>false</value>
                  </property>
               </properties>
               <field table="F5542112" name="TLEXR1" xsi:type="column"/>
               <attribute-classification>java.lang.String</attribute-classification>
            </attribute-mapping>
            <attribute-mapping xsi:type="direct-mapping">
               <attribute-name>tldtys</attribute-name>
               <properties>
                  <property name="enabled">
                     <value>false</value>
                  </property>
               </properties>
               <field table="F5542112" name="TLDTYS" xsi:type="column"/>
               <attribute-classification>java.lang.String</attribute-classification>
            </attribute-mapping>
            <attribute-mapping xsi:type="direct-mapping">
               <attribute-name>tluom1</attribute-name>
               <properties>
                  <property name="enabled">
                     <value>false</value>
                  </property>
               </properties>
               <field table="F5542112" name="TLUOM1" xsi:type="column"/>
               <attribute-classification>java.lang.String</attribute-classification>
            </attribute-mapping>
            <attribute-mapping xsi:type="direct-mapping">
               <attribute-name>tluom4</attribute-name>
               <field table="F5542112" name="TLUOM4" xsi:type="column"/>
               <attribute-classification>java.lang.String</attribute-classification>
            </attribute-mapping>
            <attribute-mapping xsi:type="direct-mapping">
               <attribute-name>tlcrcd</attribute-name>
               <field table="F5542112" name="TLCRCD" xsi:type="column"/>
               <attribute-classification>java.lang.String</attribute-classification>
            </attribute-mapping>
            <attribute-mapping xsi:type="direct-mapping">
               <attribute-name>tltorg</attribute-name>
               <properties>
                  <property name="enabled">
                     <value>false</value>
                  </property>
               </properties>
               <field table="F5542112" name="TLTORG" xsi:type="column"/>
               <attribute-classification>java.lang.String</attribute-classification>
            </attribute-mapping>
            <attribute-mapping xsi:type="direct-mapping">
               <attribute-name>tlpid</attribute-name>
               <properties>
                  <property name="enabled">
                     <value>false</value>
                  </property>
               </properties>
               <field table="F5542112" name="TLPID" xsi:type="column"/>
               <attribute-classification>java.lang.String</attribute-classification>
            </attribute-mapping>
            <attribute-mapping xsi:type="direct-mapping">
               <attribute-name>tljobn</attribute-name>
               <properties>
                  <property name="enabled">
                     <value>false</value>
                  </property>
               </properties>
               <field table="F5542112" name="TLJOBN" xsi:type="column"/>
               <attribute-classification>java.lang.String</attribute-classification>
            </attribute-mapping>
            <attribute-mapping xsi:type="direct-mapping">
               <attribute-name>tluser</attribute-name>
               <properties>
                  <property name="enabled">
                     <value>false</value>
                  </property>
               </properties>
               <field table="F5542112" name="TLUSER" xsi:type="column"/>
               <attribute-classification>java.lang.String</attribute-classification>
            </attribute-mapping>
            <attribute-mapping xsi:type="direct-mapping">
               <attribute-name>tlupmt</attribute-name>
               <properties>
                  <property name="enabled">
                     <value>false</value>
                  </property>
               </properties>
               <field table="F5542112" name="TLUPMT" xsi:type="column"/>
               <attribute-classification>java.math.BigDecimal</attribute-classification>
            </attribute-mapping>
            <attribute-mapping xsi:type="direct-mapping">
               <attribute-name>tlupmj</attribute-name>
               <properties>
                  <property name="enabled">
                     <value>false</value>
                  </property>
               </properties>
               <field table="F5542112" name="TLUPMJ" xsi:type="column"/>
               <attribute-classification>java.lang.Integer</attribute-classification>
            </attribute-mapping>
            <attribute-mapping xsi:type="direct-mapping">
               <attribute-name>tlbcrc</attribute-name>
               <properties>
                  <property name="enabled">
                     <value>false</value>
                  </property>
               </properties>
               <field table="F5542112" name="TLBCRC" xsi:type="column"/>
               <attribute-classification>java.lang.String</attribute-classification>
            </attribute-mapping>
            <attribute-mapping xsi:type="direct-mapping">
               <attribute-name>tly55Soaac</attribute-name>
               <properties>
                  <property name="enabled">
                     <value>false</value>
                  </property>
               </properties>
               <field table="F5542112" name="TLY55SOAAC" xsi:type="column"/>
               <attribute-classification>java.lang.String</attribute-classification>
            </attribute-mapping>
            <attribute-mapping xsi:type="direct-mapping">
               <attribute-name>tly55Intst</attribute-name>
               <field table="F5542112" name="TLY55INTST" xsi:type="column"/>
               <attribute-classification>java.lang.String</attribute-classification>
            </attribute-mapping>
            <attribute-mapping xsi:type="direct-mapping">
               <attribute-name>tlflag</attribute-name>
               <properties>
                  <property name="enabled">
                     <value>false</value>
                  </property>
               </properties>
               <field table="F5542112" name="TLFLAG" xsi:type="column"/>
               <attribute-classification>java.lang.String</attribute-classification>
            </attribute-mapping>
            <attribute-mapping xsi:type="direct-mapping">
               <attribute-name>tlurrf</attribute-name>
               <properties>
                  <property name="enabled">
                     <value>false</value>
                  </property>
               </properties>
               <field table="F5542112" name="TLURRF" xsi:type="column"/>
               <attribute-classification>java.lang.String</attribute-classification>
            </attribute-mapping>
            <attribute-mapping xsi:type="direct-mapping">
               <attribute-name>tlurab</attribute-name>
               <properties>
                  <property name="enabled">
                     <value>false</value>
                  </property>
               </properties>
               <field table="F5542112" name="TLURAB" xsi:type="column"/>
               <attribute-classification>java.math.BigDecimal</attribute-classification>
            </attribute-mapping>
            <attribute-mapping xsi:type="direct-mapping">
               <attribute-name>tlurdt</attribute-name>
               <properties>
                  <property name="enabled">
                     <value>false</value>
                  </property>
               </properties>
               <field table="F5542112" name="TLURDT" xsi:type="column"/>
               <attribute-classification>java.lang.Integer</attribute-classification>
            </attribute-mapping>
            <attribute-mapping xsi:type="direct-mapping">
               <attribute-name>tlurcd</attribute-name>
               <properties>
                  <property name="enabled">
                     <value>false</value>
                  </property>
               </properties>
               <field table="F5542112" name="TLURCD" xsi:type="column"/>
               <attribute-classification>java.lang.String</attribute-classification>
            </attribute-mapping>
            <attribute-mapping xsi:type="direct-mapping">
               <attribute-name>tlurat</attribute-name>
               <properties>
                  <property name="enabled">
                     <value>false</value>
                  </property>
               </properties>
               <field table="F5542112" name="TLURAT" xsi:type="column"/>
               <attribute-classification>java.math.BigDecimal</attribute-classification>
            </attribute-mapping>
            <attribute-mapping xsi:type="direct-mapping">
               <attribute-name>tly55Char1</attribute-name>
               <properties>
                  <property name="enabled">
                     <value>false</value>
                  </property>
               </properties>
               <field table="F5542112" name="TLY55CHAR1" xsi:type="column"/>
               <attribute-classification>java.lang.String</attribute-classification>
            </attribute-mapping>
            <attribute-mapping xsi:type="direct-mapping">
               <attribute-name>tly55Char2</attribute-name>
               <properties>
                  <property name="enabled">
                     <value>false</value>
                  </property>
               </properties>
               <field table="F5542112" name="TLY55CHAR2" xsi:type="column"/>
               <attribute-classification>java.lang.String</attribute-classification>
            </attribute-mapping>
            <attribute-mapping xsi:type="direct-mapping">
               <attribute-name>tly55Strg1</attribute-name>
               <properties>
                  <property name="enabled">
                     <value>false</value>
                  </property>
               </properties>
               <field table="F5542112" name="TLY55STRG1" xsi:type="column"/>
               <attribute-classification>java.lang.String</attribute-classification>
            </attribute-mapping>
            <attribute-mapping xsi:type="direct-mapping">
               <attribute-name>tly55Strg2</attribute-name>
               <properties>
                  <property name="enabled">
                     <value>false</value>
                  </property>
               </properties>
               <field table="F5542112" name="TLY55STRG2" xsi:type="column"/>
               <attribute-classification>java.lang.String</attribute-classification>
            </attribute-mapping>
            <attribute-mapping xsi:type="direct-mapping">
               <attribute-name>tly55Dte1</attribute-name>
               <properties>
                  <property name="enabled">
                     <value>false</value>
                  </property>
               </properties>
               <field table="F5542112" name="TLY55DTE1" xsi:type="column"/>
               <attribute-classification>java.lang.Integer</attribute-classification>
            </attribute-mapping>
            <attribute-mapping xsi:type="direct-mapping">
               <attribute-name>tly55Dte2</attribute-name>
               <properties>
                  <property name="enabled">
                     <value>false</value>
                  </property>
               </properties>
               <field table="F5542112" name="TLY55DTE2" xsi:type="column"/>
               <attribute-classification>java.lang.Integer</attribute-classification>
            </attribute-mapping>
            <attribute-mapping xsi:type="direct-mapping">
               <attribute-name>tly55Amnt1</attribute-name>
               <properties>
                  <property name="enabled">
                     <value>false</value>
                  </property>
               </properties>
               <field table="F5542112" name="TLY55AMNT1" xsi:type="column"/>
               <attribute-classification>java.math.BigDecimal</attribute-classification>
            </attribute-mapping>
            <attribute-mapping xsi:type="direct-mapping">
               <attribute-name>tly55Amnt2</attribute-name>
               <properties>
                  <property name="enabled">
                     <value>false</value>
                  </property>
               </properties>
               <field table="F5542112" name="TLY55AMNT2" xsi:type="column"/>
               <attribute-classification>java.math.BigDecimal</attribute-classification>
            </attribute-mapping>
            <attribute-mapping xsi:type="direct-mapping">
               <attribute-name>tly55Time1</attribute-name>
               <properties>
                  <property name="enabled">
                     <value>false</value>
                  </property>
               </properties>
               <field table="F5542112" name="TLY55TIME1" xsi:type="column"/>
               <attribute-classification>java.math.BigDecimal</attribute-classification>
            </attribute-mapping>
            <attribute-mapping xsi:type="direct-mapping">
               <attribute-name>tly55Time2</attribute-name>
               <properties>
                  <property name="enabled">
                     <value>false</value>
                  </property>
               </properties>
               <field table="F5542112" name="TLY55TIME2" xsi:type="column"/>
               <attribute-classification>java.math.BigDecimal</attribute-classification>
            </attribute-mapping>
         </attribute-mappings>
         <descriptor-type>independent</descriptor-type>
         <caching>
            <cache-type>weak-reference</cache-type>
            <cache-size>-1</cache-size>
            <always-refresh>true</always-refresh>
         </caching>
         <remote-caching>
            <cache-type>weak-reference</cache-type>
            <cache-size>-1</cache-size>
         </remote-caching>
         <instantiation/>
         <copying xsi:type="instantiation-copy-policy"/>
         <tables>
            <table name="F5542112"/>
         </tables>
         <structure>structureName</structure>
      </class-mapping-descriptor>
   </class-mapping-descriptors>
   <login xsi:type="database-login">
      <platform-class>org.eclipse.persistence.platform.database.oracle.Oracle9Platform</platform-class>
      <connection-url></connection-url>
   </login>
</object-persistence>
