<?xml version="1.0" encoding="windows-1252" ?>
<adfc-config xmlns="http://xmlns.oracle.com/adf/controller" version="1.2">
  <task-flow-definition id="UserDisplayTaskFlow">
    <default-activity id="__5">UserDisplay</default-activity>
    <managed-bean id="__2">
      <managed-bean-name id="__3">UserDisplayBean</managed-bean-name>
      <managed-bean-class id="__4">com.sfr.engage.userdisplaytaskflow.UserDisplayBean</managed-bean-class>
      <managed-bean-scope id="__1">pageFlow</managed-bean-scope>
    </managed-bean>
    <view id="UserDisplay">
      <page>/WEB-INF/com/sfr/engage/userdisplaytaskflow/UserDisplay.jsff</page>
    </view>
    <use-page-fragments/>
  </task-flow-definition>
</adfc-config>
